opentelemetry/instrumentation/click/__init__.py
opentelemetry/instrumentation/click/package.py
opentelemetry/instrumentation/click/version.py
opentelemetry_instrumentation_click-0.60b0.dist-info/METADATA
opentelemetry_instrumentation_click-0.60b0.dist-info/WHEEL
opentelemetry_instrumentation_click-0.60b0.dist-info/entry_points.txt
opentelemetry_instrumentation_click-0.60b0.dist-info/RECORD
